input_checker/__init__.py
input_checker/_version.py
input_checker/checker.py
input_checker/exceptions.py
tests/__init__.py
tests/conftest.py
tests/test_Exceptions.py
tests/test_InputChecker.py
input_checker-0.3.9.dist-info/LICENSE
input_checker-0.3.9.dist-info/METADATA
input_checker-0.3.9.dist-info/WHEEL
input_checker-0.3.9.dist-info/top_level.txt
input_checker-0.3.9.dist-info/RECORD
