Metadata-Version: 2.1
Name: input-checker
Version: 0.3.9
Summary: Package to perform comparison between data frames
Home-page: UNKNOWN
Author: LV GI Data Science Team
Author-email: #DataSciencePackages@lv.co.uk
License: UNKNOWN
Platform: UNKNOWN
Classifier: Programming Language :: Python
Classifier: Programming Language :: Python :: 3
Classifier: Programming Language :: Python :: 3.6
Classifier: Programming Language :: Python :: 3.7
Classifier: Programming Language :: Python :: 3.8
Classifier: Operating System :: OS Independent
Classifier: License :: OSI Approved :: BSD License
Requires-Python: >=3.6
Requires-Dist: tubular (>=0.2.10)
